folder_organizer_tool-1.0.0.dist-info/licenses/LICENSE
organizer/__init__.py
organizer/cli.py
organizer/core.py
folder_organizer_tool-1.0.0.dist-info/METADATA
folder_organizer_tool-1.0.0.dist-info/WHEEL
folder_organizer_tool-1.0.0.dist-info/entry_points.txt
folder_organizer_tool-1.0.0.dist-info/top_level.txt
folder_organizer_tool-1.0.0.dist-info/RECORD
