Metadata-Version: 2.4
Name: folder-organizer-tool
Version: 1.0.0
Summary: A CLI tool to organize files based on file type and extension.
Home-page: 
Author: Qazi Arsalan Shah
Project-URL: Source, https://github.com/qazi112
Project-URL: Tracker, https://github.com/qazi112
Classifier: Programming Language :: Python :: 3
Classifier: License :: OSI Approved :: MIT License
Classifier: Operating System :: OS Independent
Requires-Python: >=3.7
License-File: LICENSE
Requires-Dist: rich>=13.0
Dynamic: author
Dynamic: classifier
Dynamic: description
Dynamic: description-content-type
Dynamic: license-file
Dynamic: project-url
Dynamic: requires-dist
Dynamic: requires-python
Dynamic: summary
